MANIFEST.in
README.rst
buildout.cfg
setup.py
antispoofing/__init__.py
antispoofing.optflow.egg-info/PKG-INFO
antispoofing.optflow.egg-info/SOURCES.txt
antispoofing.optflow.egg-info/dependency_links.txt
antispoofing.optflow.egg-info/entry_points.txt
antispoofing.optflow.egg-info/namespace_packages.txt
antispoofing.optflow.egg-info/requires.txt
antispoofing.optflow.egg-info/top_level.txt
antispoofing.optflow.egg-info/zip-safe
antispoofing/optflow/__init__.py
antispoofing/optflow/bao.py
antispoofing/optflow/histocomp.py
antispoofing/optflow/kolldraw.py
antispoofing/optflow/kollreider.py
antispoofing/optflow/version.py
antispoofing/optflow/windowing.py
antispoofing/optflow/script/__init__.py
antispoofing/optflow/script/bao.py
antispoofing/optflow/script/histocomp.py
antispoofing/optflow/script/kollreider.py
antispoofing/optflow/script/kollreider_annotate.py
antispoofing/optflow/script/liu.py
antispoofing/optflow/script/score_analysis.py