Metadata-Version: 1.0
Name: antispoofing.optflow
Version: 2.0.0
Summary: Optical Flow counter-measures for the REPLAY-ATTACK database
Home-page: http://pypi.python.org/pypi/antispoofing.optflow
Author: Andre Anjos
Author-email: andre.anjos@idiap.ch
License: GPLv3
Platform: UNKNOWN
